{
  "resource_state": 2,
  "athlete": {
    "id": 123537543,
    "resource_state": 1
  },
  "name": "Night Walk",
  "distance": 6801.5,
  "moving_time": 4806,
  "elapsed_time": 5429,
  "total_elevation_gain": 15.5,
  "type": "Walk",
  "sport_type": "Walk",
  "device_name": "Samsung Health",
  "id": 14706742895,
  "start_date": "2025-06-05T16:19:37Z",
  "start_date_local": "2025-06-05T21:49:37Z",
  "timezone": "(GMT+05:30) Asia/Kolkata",
  "utc_offset": 19800.0,
  "location_city": null,
  "location_state": null,
  "location_country": null,
  "achievement_count": 0,
  "kudos_count": 0,
  "comment_count": 0,
  "athlete_count": 1,
  "photo_count": 0,
  "map": {
    "id": "a14706742895",
    "summary_polyline": "spbnA_fwhN?ADAT@I?@@AKFWCQFMJo@ASEIFq@AMDWAKGMBI@a@HSAMCKECWBUEE@QEWAWG]?_@IIAA@_@Ek@K_@CCC_@CECsAOc@KYMCE@OPu@DG?YTc@AQFSCKJ_AAGKM?Cw@_@Wc@?GFIBGGi@?c@CAEEK?YHs@DeBRGCaAPU?u@FEBM@KD[?a@DIB_@@QDm@F]Ja@?a@HECO?GOAOHS@WRo@B[DO?KPg@D_@H_@?ITo@Ls@CIUEECICa@SGGIGaAQMIUKUCWIYCKGA@GCMQKEUAWGk@[YCSGEEo@MkBk@q@OQKSAMGC@SCGG[I}@K_@Mi@MSCEBMAEAC?s@QACYASIc@CcA_@]@CB[IOISCKEi@?@\\IRBTGXGJI`@APCL@\\EXY~@Ep@GR@LE^@PM\\If@IfAEHEb@GN?ZMb@CPBXKj@GHMt@?j@Mf@Ch@GTCXEJ?LKd@AT@JCPGBM@WEW?MEED?JBDH@LHJ@f@KVB`@EDCJ?HCTEN@`@Cf@Qt@I`@KP?NEZEd@Od@CHGFBP?RIj@C|A_@h@Ch@Il@GfB_@hBM`AORIpAWJ@NGj@I@Cp@Gv@QB@BADF`@CpAUNNMj@Js@F@FA@BXEL?PGTCPBHCBJERHi@P@NC^A@C`@A^Il@ATGR?ZKf@?j@MXEX?`@KZ?RET?JCV@TKPE^?LIDBLGJ?BD`AZRJb@JRPf@RPDx@`@f@N`Ab@LBl@TJF\\PNDHA`@VH?d@TbBb@`@Tr@RDDJ@XRBAVDLDBDLF@BZPCl@Mj@?FIZMXGb@IL?FBDNADGKTOKU?SEIBOKG?IDMAGBCD?|@BXBt@BJCh@FT?HBH@bAC^DRBt@?`@CZ?fAAREDm@GUEIBBd@Cb@@N?Z@FEVDbANd@DAB`@Vj@@HCFBDD@BHdABHFH?BABDA\\E`@@l@ELB\\FPTZB?HF?FHNFh@Lt@PdCFRCP?p@MrAGNAP@VBHCX",
    "resource_state": 2
  },
  "trainer": false,
  "commute": false,
  "manual": false,
  "private": false,
  "visibility": "everyone",
  "flagged": false,
  "gear_id": "g21682779",
  "start_latlng": [
    12.960979,
    80.24088
  ],
  "end_latlng": [
    12.959454,
    80.2341
  ],
  "average_speed": 1.415,
  "max_speed": 12.097,
  "average_cadence": 108.2,
  "has_heartrate": true,
  "average_heartrate": 117.1,
  "max_heartrate": 137.0,
  "heartrate_opt_out": false,
  "display_hide_heartrate_option": true,
  "elev_high": 9.3,
  "elev_low": 3.0,
  "upload_id": 15693984153,
  "upload_id_str": "15693984153",
  "external_id": "shealthf1a9bdbb-5a74-43d4-a65a-c1cd20f28173.tcx",
  "from_accepted_tag": false,
  "pr_count": 0,
  "total_photo_count": 0,
  "has_kudoed": false
}