{
  "resource_state": 2,
  "athlete": {
    "id": 123537543,
    "resource_state": 1
  },
  "name": "Afternoon Walk",
  "distance": 13422.7,
  "moving_time": 10068,
  "elapsed_time": 10855,
  "total_elevation_gain": 11.6,
  "type": "Walk",
  "sport_type": "Walk",
  "device_name": "Samsung Health",
  "id": 15198142625,
  "start_date": "2025-07-22T10:47:52Z",
  "start_date_local": "2025-07-22T16:17:52Z",
  "timezone": "(GMT+05:30) Asia/Kolkata",
  "utc_offset": 19800.0,
  "location_city": null,
  "location_state": null,
  "location_country": null,
  "achievement_count": 0,
  "kudos_count": 0,
  "comment_count": 0,
  "athlete_count": 1,
  "photo_count": 0,
  "map": {
    "id": "a15198142625",
    "summary_polyline": "i{nmA}cthNNo@WO_AF{AC_C@o@HaAAGDi@?MDUEgA?CGKCSFo@BCEsBGYBk@Gm@?e@G_@HaD@YFaDNo@J{ADcBAQKy@Fs@K}ESg@Gm@?g@JGKPp@DBw@y@CLE@?IKCaAKw@Du@I{@@m@EeABcAGaAF_@Oe@@}D]wADm@I]Fa@CII_@A_@@[Ti@K]?YEkBLOC_@FECKDkA?a@Dk@@KD_AEkAFCD}CG_AHuFE}BJEG@@e@ESBq@Gm@JGCwACqADeAAEB}@BMGkAC}AM_C[aAYoBQQG{@Ek@KiHM}C?c@BqFC{@DGEyAAoAKOFcCUk@IkAJEEAHDXMZ@RGu@LEIS@GiAMUBWCMHs@MaA?KGe@BKE[D}@KUJyAGqAI_B?BA]Ek@BiBKs@Fq@Im@BqAGg@Ig@BuAESD_BGo@Ha@Sa@E]BMI_@E[HYEW?CDIE]?IFGAGIe@Ee@B{AG{A@gDEKEUBw@EECu@@kBEaCQ{CEm@OyEc@G@WGOD_@Qe@?k@Ku@@MKkAMo@D[O{BOo@MmBCSIg@Km@DYMABUAi@BYECEQ?CFMG}AK}@SwBEWG}@Gk@@e@Qk@DIK{BKgAQ_DOe@@]OGFBBSKk@GMGSFIIY@y@O[DY@kCSu@Mg@?uAGk@MaBKc@?eC]a@AsC[_G]g@I[?e@JyCQwAUwACKEeAAw@KsCCSOqACs@Q{AIo@OaAGKMe@KW?uAUgA]ODa@Ss@OWQUAi@SM?WMiAIWM}@Sa@WIBOKQEIMc@AOOg@W}@]mB_@}@a@KOsC}@USsA[kAk@sCcAEIuAa@w@c@gCw@[SWCe@MWS]OUCKMaCe@O@YIo@EeDs@q@GsBk@SB[COEu@?w@IYJMN_AFWDcA]q@Q[Ok@I_@Oi@AIIy@IGGUCSIsBU{Aa@SAaE}@o@EcDu@CJCdCGf@G@KNBLSRM\\C?]SE]B_BHe@AETeA?OOI}AEe@QmAMo@Q_@WOC?B{@]kAo@sA_@m@J_@Cw@?wCm@{@GWQ_@@i@I_@F@t@Cd@HPI^El@?fAOfA@TECBDWp@e@DeAG]I_B@OMG?@MECEBOJAHYFWI_AG[LElBEFoACc@FyA^m@@eAVATFxAGTCl@BNU~@IdAENOB{@EKB",
    "resource_state": 2
  },
  "trainer": false,
  "commute": false,
  "manual": false,
  "private": false,
  "visibility": "everyone",
  "flagged": false,
  "gear_id": "g21682779",
  "start_latlng": [
    12.861195,
    80.225075
  ],
  "end_latlng": [
    12.959192,
    80.23407
  ],
  "average_speed": 1.333,
  "max_speed": 8.989,
  "average_cadence": 105.5,
  "has_heartrate": true,
  "average_heartrate": 118.7,
  "max_heartrate": 148.0,
  "heartrate_opt_out": false,
  "display_hide_heartrate_option": true,
  "elev_high": 8.0,
  "elev_low": 2.3,
  "upload_id": 16230279726,
  "upload_id_str": "16230279726",
  "external_id": "shealth94a02c2c-8624-46b6-8ec2-27dfc7532e92.tcx",
  "from_accepted_tag": false,
  "pr_count": 0,
  "total_photo_count": 0,
  "has_kudoed": false
}